rocksdb_statistics/__init__.py
rocksdb_statistics/__main__.py
rocksdb_statistics/rocksdb_statistics.py
rocksdb_statistics-0.0.10.dist-info/entry_points.txt
rocksdb_statistics-0.0.10.dist-info/LICENSE
rocksdb_statistics-0.0.10.dist-info/WHEEL
rocksdb_statistics-0.0.10.dist-info/METADATA
rocksdb_statistics-0.0.10.dist-info/RECORD
